libtorrent-stubs/__init__.pyi
libtorrent-stubs/py.typed
types_libtorrent-2.0.11.20250816.dist-info/METADATA
types_libtorrent-2.0.11.20250816.dist-info/WHEEL
types_libtorrent-2.0.11.20250816.dist-info/top_level.txt
types_libtorrent-2.0.11.20250816.dist-info/RECORD
