Metadata-Version: 2.4
Name: types-libtorrent
Version: 2.0.11.20250816
Summary: Type stubs for python-libtorrent
Author-email: David White <david@runonflux.io>
License-Expression: MIT
Project-URL: Homepage, https://github.com/python/typeshed
Project-URL: Repository, https://github.com/python/typeshed
Keywords: typing,stubs,libtorrent,bittorrent
Classifier: Development Status :: 4 - Beta
Classifier: Intended Audience :: Developers
Classifier: Programming Language :: Python :: 3
Classifier: Programming Language :: Python :: 3.8
Classifier: Programming Language :: Python :: 3.9
Classifier: Programming Language :: Python :: 3.10
Classifier: Programming Language :: Python :: 3.11
Classifier: Programming Language :: Python :: 3.12
Classifier: Programming Language :: Python :: 3.13
Classifier: Topic :: Software Development :: Libraries :: Python Modules
Classifier: Topic :: Internet :: File Transfer Protocol (FTP)
Classifier: Topic :: System :: Networking
Classifier: Typing :: Stubs Only
Requires-Python: >=3.8
